pytalog/polars/__init__.py
pytalog/polars/data_sources/__init__.py
pytalog/polars/data_sources/file.py
pytalog/polars/data_sources/sql.py
pytalog_polars-0.1.1.dist-info/METADATA
pytalog_polars-0.1.1.dist-info/WHEEL
pytalog_polars-0.1.1.dist-info/top_level.txt
pytalog_polars-0.1.1.dist-info/RECORD
