Metadata-Version: 2.1
Name: pytalog-polars
Version: 0.1.1
Requires-Dist: pytalog-base==0.1.1
Requires-Dist: polars>=1.1.0
Provides-Extra: dev
Requires-Dist: pytalog-base==0.1.1; extra == "dev"
Requires-Dist: polars==1.1.0; extra == "dev"
Requires-Dist: xlsxwriter==3.2.0; extra == "dev"
Requires-Dist: fastexcel==0.11.5; extra == "dev"
Requires-Dist: sqlalchemy==2.0.31; extra == "dev"
Provides-Extra: strict
Requires-Dist: pytalog-base==0.1.1; extra == "strict"
Requires-Dist: polars==1.1.0; extra == "strict"
